aptus/icon48.png
aptus/palettes.py
aptus/__init__.py
aptus/options.py
aptus/icon16.png
aptus/timeutil.py
aptus/engine.cpython-39-x86_64-linux-gnu.so
aptus/splash.png
aptus/progress.py
aptus/settings.py
aptus/ggr.py
aptus/compute.py
aptus/icon32.png
aptus/cmdline.py
aptus/web/__init__.py
aptus/web/server.py
aptus/web/static/aptus.js
aptus/web/static/style.scss
aptus/web/static/style.css
aptus/web/templates/mainpage.html
aptus/web/templates/icon_close.svg
aptus/gui/viewpanel.py
aptus/gui/dictpanel.py
aptus/gui/resources.py
aptus/gui/help.py
aptus/gui/__init__.py
aptus/gui/palettespanel.py
aptus/gui/computepanel.py
aptus/gui/statspanel.py
aptus/gui/mainframe.py
aptus/gui/juliapanel.py
aptus/gui/ids.py
aptus/gui/pointinfo.py
aptus/gui/youarehere.py
aptus/gui/misc.py
aptus/palettes/redblue.ggr
aptus/palettes/ib15.ggr
aptus/palettes/DEM_screen.ggr
aptus/palettes/ib18.ggr
aptus/palettes/bluefly.ggr
Aptus-3.0.1.dist-info/METADATA
Aptus-3.0.1.dist-info/top_level.txt
Aptus-3.0.1.dist-info/RECORD
Aptus-3.0.1.dist-info/WHEEL
Aptus-3.0.1.dist-info/entry_points.txt
